dtws1/__init__.py
dtws1/colorutil.py
dtws1/dtws1.py
dtws1/gif.py
dtws1/heatmap.py
dtws1/maputil.py
dtws1/plotutil.py
dtws1/timeutil.py
dtws1/trajectory.py
dtws1-0.3.1.dist-info/LICENSE
dtws1-0.3.1.dist-info/METADATA
dtws1-0.3.1.dist-info/WHEEL
dtws1-0.3.1.dist-info/top_level.txt
dtws1-0.3.1.dist-info/RECORD
