Metadata-Version: 2.1
Name: dtws1
Version: 0.3.1
Summary: tools for data science
Home-page: https://github.com/hotoku-dtws/dtws1
Author: Yasunori Horikoshi
Author-email: yasunori_horikoshi@datawise.co.jp
License: MIT license
Keywords: dtws1
Platform: UNKNOWN
Classifier: Development Status :: 2 - Pre-Alpha
Classifier: Intended Audience :: Developers
Classifier: License :: OSI Approved :: MIT License
Classifier: Natural Language :: English
Classifier: Programming Language :: Python :: 3
Classifier: Programming Language :: Python :: 3.5
Classifier: Programming Language :: Python :: 3.6
Classifier: Programming Language :: Python :: 3.7
Classifier: Programming Language :: Python :: 3.8
Requires-Python: >=3.5
Requires-Dist: colormath
Requires-Dist: folium
Requires-Dist: geojson
Requires-Dist: geopy
Requires-Dist: h3
Requires-Dist: matplotlib
Requires-Dist: numpy
Requires-Dist: pandas
Requires-Dist: pyproj
Requires-Dist: tilemapbase
